quantstyles/__init__.py
quantstyles/generate_quantcmaps.py
quantstyles/get_cpt.py
quantstyles/quantcmaps.py
quantstyles/style_installed.flag
quantstyles/colormaps/colormaps.jl
quantstyles/colormaps/cyclic_quantcyclicjet_30-81_c58_n256.cpt
quantstyles/colormaps/diverging_quantbwr_33-96_c32_n256.cpt
quantstyles/colormaps/diverging_quantcoolwarm_40-95_c42_n256.cpt
quantstyles/colormaps/linear_black_blue_0-70_c24_n256.cpt
quantstyles/colormaps/linear_black_darkpurple_0-70_c24_n256.cpt
quantstyles/colormaps/linear_black_darkyellow_0-70_c40_n256.cpt
quantstyles/colormaps/linear_black_green_0-70_c30_n256.cpt
quantstyles/colormaps/linear_black_mnfred_0-70_c33_n256.cpt
quantstyles/colormaps/linear_black_orange_0-70_c35_n256.cpt
quantstyles/colormaps/linear_blue_white_40-100_c24_n256.cpt
quantstyles/colormaps/linear_darkpurple_white_40-100_c24_n256.cpt
quantstyles/colormaps/linear_darkyellow_white_40-100_c37_n256.cpt
quantstyles/colormaps/linear_green_white_40-100_c30_n256.cpt
quantstyles/colormaps/linear_mnfred_white_40-100_c33_n256.cpt
quantstyles/colormaps/linear_orange_white_40-100_c34_n256.cpt
quantstyles/colormaps/linear_quanthot_0-100_c60_n256.cpt
quantstyles/colormaps/linear_quantjet_33-81_c60_n256.cpt
quantstyles/colormaps/linear_quantjetuniform_33-81_c61_n256.cpt
quantstyles/colormaps/linear_quantparrot_20-95_c47_n256.cpt
quantstyles/colormaps/linear_quantplasma_15-100_c52_n256.cpt
quantstyles/stylelib/quant.mplstyle
quantstyles-0.107.dist-info/LICENSE.txt
quantstyles-0.107.dist-info/METADATA
quantstyles-0.107.dist-info/WHEEL
quantstyles-0.107.dist-info/top_level.txt
quantstyles-0.107.dist-info/RECORD
