Metadata-Version: 2.1
Name: quantstyles
Version: 0.107
Summary: Matplotlib styles for scientific usage
Home-page: https://github.com/Trel725/quantstyles
Author: Andrii Trelin
Author-email: andrii.trelin@uni-rostock.de
License: MIT
Download-URL: https://pypi.org/project/quantstyles/
Platform: UNKNOWN
Requires-Dist: matplotlib
